hackerakos/__init__.py
hackerakos/src/__init__.py
hackerakos/src/hackerakos.py
hackerakos/src/utils.py
hackerakos-0.0.10.dist-info/LICENSE
hackerakos-0.0.10.dist-info/METADATA
hackerakos-0.0.10.dist-info/WHEEL
hackerakos-0.0.10.dist-info/top_level.txt
hackerakos-0.0.10.dist-info/RECORD
