Metadata-Version: 2.1
Name: hackerakos
Version: 0.0.10
Summary: Hackerakos library
Home-page: http://hacker-bin.com
Author: Hackerakos
Author-email: hackerakos@hacker-bin.com
License: MIT
Classifier: License :: OSI Approved :: MIT License
Classifier: Programming Language :: Python :: 3.12
Classifier: Operating System :: OS Independent
Requires-Python: >=3.10
License-File: LICENSE
Provides-Extra: dev
Requires-Dist: pytest>=7.0; extra == "dev"
Requires-Dist: twine>=4.0.2; extra == "dev"
